github/github.py
github/manifest.toml
opsbox_github_output-0.1.4.dist-info/LICENCE.txt
opsbox_github_output-0.1.4.dist-info/METADATA
opsbox_github_output-0.1.4.dist-info/WHEEL
opsbox_github_output-0.1.4.dist-info/entry_points.txt
opsbox_github_output-0.1.4.dist-info/top_level.txt
opsbox_github_output-0.1.4.dist-info/RECORD
